LICENSE
MANIFEST.in
README.rst
setup.py
django_tethys_compute.egg-info/PKG-INFO
django_tethys_compute.egg-info/SOURCES.txt
django_tethys_compute.egg-info/dependency_links.txt
django_tethys_compute.egg-info/requires.txt
django_tethys_compute.egg-info/top_level.txt
tethys_compute/__init__.py
tethys_compute/admin.py
tethys_compute/apps.py
tethys_compute/models.py
tethys_compute/tests.py
tethys_compute/urls.py
tethys_compute/views.py
tethys_compute/migrations/0001_initial.py
tethys_compute/migrations/0002_auto_20150206_0433.py
tethys_compute/migrations/__init__.py
tethys_compute/static/tethys_compute/css/table.css
tethys_compute/static/tethys_compute/img/loader.gif
tethys_compute/static/tethys_compute/js/cluster_index.js
tethys_compute/templates/tethys_compute/cluster_index.html