Metadata-Version: 1.1
Name: django-tethys-compute
Version: 0.0.2
Summary: A Django app for adding computing resources admin controls to Tethys .
Home-page: https://github.com/CI-WATER/TethysCluster/wiki
Author: Scott Christensen
Author-email: sdc50@byu.net
License: BSD 2-Clause License
Platform: UNKNOWN
Classifier: Environment :: Web Environment
Classifier: Framework :: Django
Classifier: Intended Audience :: Developers
Classifier: License :: OSI Approved :: BSD License
Classifier: Operating System :: OS Independent
Classifier: Programming Language :: Python
Classifier: Programming Language :: Python :: 2
Classifier: Programming Language :: Python :: 2.7
Classifier: Topic :: Internet :: WWW/HTTP
Classifier: Topic :: Internet :: WWW/HTTP :: Dynamic Content
